[
    {
        "key": "group_617435a38ca44",
        "title": "section_1",
        "fields": [
            {
                "key": "field_61754c0a475a5",
                "label": "logo ikona",
                "name": "logo_ikona",
                "type": "image",
                "instructions": "",
                "required": 0,
                "conditional_logic": 0,
                "wrapper": {
                    "width": "",
                    "class": "",
                    "id": ""
                },
                "return_format": "array",
                "preview_size": "medium",
                "library": "all",
                "min_width": "",
                "min_height": "",
                "min_size": "",
                "max_width": "",
                "max_height": "",
                "max_size": "",
                "mime_types": ""
            },
            {
                "key": "field_61754c50475a6",
                "label": "logo text",
                "name": "logo_text",
                "type": "text",
                "instructions": "",
                "required": 0,
                "conditional_logic": 0,
                "wrapper": {
                    "width": "",
                    "class": "",
                    "id": ""
                },
                "default_value": "",
                "placeholder": "",
                "prepend": "",
                "append": "",
                "maxlength": ""
            },
            {
                "key": "field_61754c6d475a7",
                "label": "phone",
                "name": "phone",
                "type": "text",
                "instructions": "",
                "required": 1,
                "conditional_logic": 0,
                "wrapper": {
                    "width": "",
                    "class": "",
                    "id": ""
                },
                "default_value": "",
                "placeholder": "",
                "prepend": "",
                "append": "",
                "maxlength": ""
            },
            {
                "key": "field_61754c91475a8",
                "label": "nagłówek_1",
                "name": "naglowek_1",
                "type": "text",
                "instructions": "",
                "required": 0,
                "conditional_logic": 0,
                "wrapper": {
                    "width": "",
                    "class": "",
                    "id": ""
                },
                "default_value": "",
                "placeholder": "",
                "prepend": "",
                "append": "",
                "maxlength": ""
            },
            {
                "key": "field_61754cb7475a9",
                "label": "nagłówek 2",
                "name": "naglowek_2",
                "type": "text",
                "instructions": "",
                "required": 0,
                "conditional_logic": 0,
                "wrapper": {
                    "width": "",
                    "class": "",
                    "id": ""
                },
                "default_value": "",
                "placeholder": "",
                "prepend": "",
                "append": "",
                "maxlength": ""
            },
            {
                "key": "field_61754cd2475aa",
                "label": "paragraf_1",
                "name": "paragraf_1",
                "type": "text",
                "instructions": "",
                "required": 0,
                "conditional_logic": 0,
                "wrapper": {
                    "width": "",
                    "class": "",
                    "id": ""
                },
                "default_value": "",
                "placeholder": "",
                "prepend": "",
                "append": "",
                "maxlength": ""
            },
            {
                "key": "field_61754d41475ac",
                "label": "fotka",
                "name": "fotka",
                "type": "image",
                "instructions": "",
                "required": 0,
                "conditional_logic": 0,
                "wrapper": {
                    "width": "",
                    "class": "",
                    "id": ""
                },
                "return_format": "array",
                "preview_size": "medium",
                "library": "all",
                "min_width": "",
                "min_height": "",
                "min_size": "",
                "max_width": "",
                "max_height": "",
                "max_size": "",
                "mime_types": ""
            },
            {
                "key": "field_6176aa5d8680c",
                "label": "link przycisk",
                "name": "link_przycisk",
                "type": "text",
                "instructions": "",
                "required": 0,
                "conditional_logic": 0,
                "wrapper": {
                    "width": "",
                    "class": "",
                    "id": ""
                },
                "default_value": "",
                "placeholder": "",
                "prepend": "",
                "append": "",
                "maxlength": ""
            }
        ],
        "location": [
            [
                {
                    "param": "block",
                    "operator": "==",
                    "value": "acf\/section-1"
                }
            ]
        ],
        "menu_order": 0,
        "position": "normal",
        "style": "default",
        "label_placement": "top",
        "instruction_placement": "label",
        "hide_on_screen": "",
        "active": true,
        "description": ""
    },
    {
        "key": "group_617550f298535",
        "title": "section_2_image_and_slider",
        "fields": [
            {
                "key": "field_61755108ca776",
                "label": "kolor kwadratu",
                "name": "kolor_kwadratu",
                "type": "color_picker",
                "instructions": "",
                "required": 1,
                "conditional_logic": 0,
                "wrapper": {
                    "width": "",
                    "class": "",
                    "id": ""
                },
                "default_value": "#eb6a15"
            },
            {
                "key": "field_6175523aca777",
                "label": "obraz",
                "name": "obraz",
                "type": "image",
                "instructions": "",
                "required": 1,
                "conditional_logic": 0,
                "wrapper": {
                    "width": "",
                    "class": "",
                    "id": ""
                },
                "return_format": "array",
                "preview_size": "medium",
                "library": "all",
                "min_width": "",
                "min_height": "",
                "min_size": "",
                "max_width": "",
                "max_height": "",
                "max_size": "",
                "mime_types": ""
            },
            {
                "key": "field_6175526bca778",
                "label": "nagłówek_1",
                "name": "naglowek_1",
                "type": "text",
                "instructions": "",
                "required": 0,
                "conditional_logic": 0,
                "wrapper": {
                    "width": "",
                    "class": "",
                    "id": ""
                },
                "default_value": "",
                "placeholder": "",
                "prepend": "",
                "append": "",
                "maxlength": ""
            },
            {
                "key": "field_61755279ca779",
                "label": "paragraf",
                "name": "paragraf",
                "type": "textarea",
                "instructions": "",
                "required": 0,
                "conditional_logic": 0,
                "wrapper": {
                    "width": "",
                    "class": "",
                    "id": ""
                },
                "default_value": "",
                "placeholder": "",
                "maxlength": "",
                "rows": "",
                "new_lines": ""
            },
            {
                "key": "field_61755288ca77a",
                "label": "nagłówek_2",
                "name": "naglowek_2",
                "type": "text",
                "instructions": "",
                "required": 0,
                "conditional_logic": 0,
                "wrapper": {
                    "width": "",
                    "class": "",
                    "id": ""
                },
                "default_value": "",
                "placeholder": "",
                "prepend": "",
                "append": "",
                "maxlength": ""
            },
            {
                "key": "field_617552caca77b",
                "label": "slider",
                "name": "slider",
                "type": "repeater",
                "instructions": "",
                "required": 1,
                "conditional_logic": 0,
                "wrapper": {
                    "width": "",
                    "class": "",
                    "id": ""
                },
                "collapsed": "",
                "min": 0,
                "max": 0,
                "layout": "table",
                "button_label": "",
                "sub_fields": [
                    {
                        "key": "field_6176b082b5ea4",
                        "label": "image",
                        "name": "image",
                        "type": "image",
                        "instructions": "",
                        "required": 0,
                        "conditional_logic": 0,
                        "wrapper": {
                            "width": "",
                            "class": "",
                            "id": ""
                        },
                        "return_format": "array",
                        "preview_size": "medium",
                        "library": "all",
                        "min_width": "",
                        "min_height": "",
                        "min_size": "",
                        "max_width": "",
                        "max_height": "",
                        "max_size": "",
                        "mime_types": ""
                    },
                    {
                        "key": "field_6176b0bbb5ea6",
                        "label": "text",
                        "name": "text",
                        "type": "text",
                        "instructions": "",
                        "required": 0,
                        "conditional_logic": 0,
                        "wrapper": {
                            "width": "",
                            "class": "",
                            "id": ""
                        },
                        "default_value": "",
                        "placeholder": "",
                        "prepend": "",
                        "append": "",
                        "maxlength": ""
                    }
                ]
            }
        ],
        "location": [
            [
                {
                    "param": "block",
                    "operator": "==",
                    "value": "acf\/section-2-image-and-slider"
                }
            ]
        ],
        "menu_order": 0,
        "position": "normal",
        "style": "default",
        "label_placement": "top",
        "instruction_placement": "label",
        "hide_on_screen": "",
        "active": true,
        "description": ""
    },
    {
        "key": "group_61769bf0a7378",
        "title": "section_3_accordion",
        "fields": [
            {
                "key": "field_61769bfa49016",
                "label": "naglowek accordion",
                "name": "naglowek_accordion",
                "type": "text",
                "instructions": "",
                "required": 0,
                "conditional_logic": 0,
                "wrapper": {
                    "width": "",
                    "class": "",
                    "id": ""
                },
                "default_value": "",
                "placeholder": "",
                "prepend": "",
                "append": "",
                "maxlength": ""
            },
            {
                "key": "field_61769c1749017",
                "label": "kafelek",
                "name": "kafelek",
                "type": "repeater",
                "instructions": "",
                "required": 0,
                "conditional_logic": 0,
                "wrapper": {
                    "width": "",
                    "class": "",
                    "id": ""
                },
                "collapsed": "",
                "min": 0,
                "max": 0,
                "layout": "table",
                "button_label": "",
                "sub_fields": [
                    {
                        "key": "field_61769c4949018",
                        "label": "naglowek",
                        "name": "naglowek",
                        "type": "text",
                        "instructions": "",
                        "required": 0,
                        "conditional_logic": 0,
                        "wrapper": {
                            "width": "",
                            "class": "",
                            "id": ""
                        },
                        "default_value": "",
                        "placeholder": "",
                        "prepend": "",
                        "append": "",
                        "maxlength": ""
                    },
                    {
                        "key": "field_61769c6649019",
                        "label": "paragraf",
                        "name": "paragraf",
                        "type": "text",
                        "instructions": "",
                        "required": 0,
                        "conditional_logic": 0,
                        "wrapper": {
                            "width": "",
                            "class": "",
                            "id": ""
                        },
                        "default_value": "",
                        "placeholder": "",
                        "prepend": "",
                        "append": "",
                        "maxlength": ""
                    }
                ]
            }
        ],
        "location": [
            [
                {
                    "param": "block",
                    "operator": "==",
                    "value": "acf\/section-3-accordion"
                }
            ]
        ],
        "menu_order": 0,
        "position": "normal",
        "style": "default",
        "label_placement": "top",
        "instruction_placement": "label",
        "hide_on_screen": "",
        "active": true,
        "description": ""
    },
    {
        "key": "group_61769d6c0b034",
        "title": "section_4_contact",
        "fields": [
            {
                "key": "field_6176a5e21ae15",
                "label": "all right services text",
                "name": "all_right_services_text",
                "type": "text",
                "instructions": "",
                "required": 1,
                "conditional_logic": 0,
                "wrapper": {
                    "width": "",
                    "class": "",
                    "id": ""
                },
                "default_value": "",
                "placeholder": "",
                "prepend": "",
                "append": "",
                "maxlength": ""
            }
        ],
        "location": [
            [
                {
                    "param": "block",
                    "operator": "==",
                    "value": "acf\/section-4-contact"
                }
            ]
        ],
        "menu_order": 0,
        "position": "normal",
        "style": "default",
        "label_placement": "top",
        "instruction_placement": "label",
        "hide_on_screen": "",
        "active": true,
        "description": ""
    }
]